halbestunde_python_client/__init__.py
halbestunde_python_client/client.py
halbestunde_python_client-0.1.1.dist-info/METADATA
halbestunde_python_client-0.1.1.dist-info/WHEEL
halbestunde_python_client-0.1.1.dist-info/RECORD
