Metadata-Version: 2.1
Name: halbestunde-python-client
Version: 0.1.1
Summary: Unofficial and open source Python library for interacting with the Halbestunde API
License: MIT
Author: Mariusz Smenżyk
Author-email: mariusz.smenzyk@bravelab.io
Requires-Python: >=3.9,<4.0
Classifier: License :: OSI Approved :: MIT License
Classifier: Programming Language :: Python :: 3
Classifier: Programming Language :: Python :: 3.9
Classifier: Programming Language :: Python :: 3.10
Classifier: Programming Language :: Python :: 3.11
Classifier: Programming Language :: Python :: 3.12
Requires-Dist: flask (>=3.0.3,<4.0.0)
Requires-Dist: requests (>=2.25.1,<3.0.0)
